agents/__init__.py
agents/decoder_agent.py
agents/event_agent.py
agents/intel_agent.py
agents/log_parser_agent.py
agents/product_agents.py
agents/report_agent.py
agents/security_qa_agent.py
agents/traffic_agent.py
agents/unified_agent.py
api/__init__.py
api/routes.py
api/routes_unified.py
api/routes_v2.py
config/config.py
core/cache.py
core/data_processor.py
core/data_storage.py
core/deepseek_api.py
core/utils.py
hos_ai_security/__init__.py
hos_ai_security/main.py
hos_ai_security/agents/__init__.py
hos_ai_security/agents/decoder_agent.py
hos_ai_security/agents/event_agent.py
hos_ai_security/agents/intel_agent.py
hos_ai_security/agents/log_parser_agent.py
hos_ai_security/agents/product_agents.py
hos_ai_security/agents/report_agent.py
hos_ai_security/agents/security_qa_agent.py
hos_ai_security/agents/traffic_agent.py
hos_ai_security/agents/unified_agent.py
hos_ai_security/api/__init__.py
hos_ai_security/api/routes.py
hos_ai_security/api/routes_unified.py
hos_ai_security/api/routes_v2.py
hos_ai_security/config/config.py
hos_ai_security/core/cache.py
hos_ai_security/core/data_processor.py
hos_ai_security/core/data_storage.py
hos_ai_security/core/deepseek_api.py
hos_ai_security/core/utils.py
hos_ai_security/monitoring/metrics_collector.py
hos_ai_security/monitoring/monitoring_api.py
hos_ai_security/scenarios/__init__.py
hos_ai_security/scenarios/attack_defense.py
hos_ai_security/scenarios/data_security.py
hos_ai_security/scenarios/detection_response.py
hos_ai_security/scenarios/knowledge_qa.py
hos_ai_security/scenarios/scenario_manager.py
hos_ai_security/scenarios/security_operation.py
hos_greed-3.0.1.dist-info/licenses/LICENSE.txt
monitoring/metrics_collector.py
monitoring/monitoring_api.py
scenarios/__init__.py
scenarios/attack_defense.py
scenarios/data_security.py
scenarios/detection_response.py
scenarios/knowledge_qa.py
scenarios/scenario_manager.py
scenarios/security_operation.py
hos_greed-3.0.1.dist-info/METADATA
hos_greed-3.0.1.dist-info/WHEEL
hos_greed-3.0.1.dist-info/entry_points.txt
hos_greed-3.0.1.dist-info/top_level.txt
hos_greed-3.0.1.dist-info/RECORD
