Metadata-Version: 2.4
Name: HOS-GREED
Version: 3.0.1
Summary: 轻量化AI安全赋能平台，适合中小型企业
Home-page: http://localhost:50000
Author: HOS Team
Author-email: HOS Team <admin@example.com>
Project-URL: Homepage, http://localhost:50000
Project-URL: Documentation, http://localhost:50000/docs
Keywords: AI,security,fastapi,deepseek,security-automation
Classifier: Programming Language :: Python :: 3
Classifier: License :: OSI Approved :: MIT License
Classifier: Operating System :: OS Independent
Classifier: Intended Audience :: Developers
Classifier: Intended Audience :: System Administrators
Classifier: Intended Audience :: Information Technology
Classifier: Topic :: Security
Classifier: Topic :: System :: Networking :: Monitoring
Requires-Python: >=3.8
License-File: LICENSE.txt
Requires-Dist: fastapi>=0.104.0
Requires-Dist: uvicorn>=0.24.0
Requires-Dist: pydantic>=2.4.0
Requires-Dist: pydantic-settings>=2.0.0
Requires-Dist: requests>=2.31.0
Requires-Dist: python-dotenv>=1.0.0
Dynamic: author
Dynamic: home-page
Dynamic: license-file
Dynamic: requires-python
